deep_learn_ai_api_client/__init__.py
deep_learn_ai_api_client/api/__init__.py
deep_learn_ai_api_client/api/api_user_management/__init__.py
deep_learn_ai_api_client/api/api_user_management/delete_api_users_id.py
deep_learn_ai_api_client/api/api_user_management/get_api_users.py
deep_learn_ai_api_client/api/api_user_management/get_api_users_id.py
deep_learn_ai_api_client/api/api_user_management/post_api_users.py
deep_learn_ai_api_client/api/api_user_management/post_api_users_id_regenerate_key.py
deep_learn_ai_api_client/api/api_user_management/put_api_users_id.py
deep_learn_ai_api_client/api/default/__init__.py
deep_learn_ai_api_client/api/default/get_health_health.py
deep_learn_ai_api_client/api/documents/__init__.py
deep_learn_ai_api_client/api/documents/delete_knowledges_id_documents_document_id.py
deep_learn_ai_api_client/api/documents/post_knowledges_id_documents.py
deep_learn_ai_api_client/api/documents/put_knowledges_id_documents_document_id.py
deep_learn_ai_api_client/api/knowledge/__init__.py
deep_learn_ai_api_client/api/knowledge/delete_knowledges_id.py
deep_learn_ai_api_client/api/knowledge/get_knowledges.py
deep_learn_ai_api_client/api/knowledge/post_knowledges.py
deep_learn_ai_api_client/api/knowledge_base/__init__.py
deep_learn_ai_api_client/api/knowledge_base/post_agents_bualoichat.py
deep_learn_ai_api_client/api/learning_content_system/__init__.py
deep_learn_ai_api_client/api/learning_content_system/post_agents_lcs_learning_path_generator.py
deep_learn_ai_api_client/client.py
deep_learn_ai_api_client/errors.py
deep_learn_ai_api_client/models/__init__.py
deep_learn_ai_api_client/models/delete_api_users_id_response_401.py
deep_learn_ai_api_client/models/delete_api_users_id_response_403.py
deep_learn_ai_api_client/models/delete_api_users_id_response_404.py
deep_learn_ai_api_client/models/delete_knowledges_id_documents_document_id_response_200.py
deep_learn_ai_api_client/models/delete_knowledges_id_documents_document_id_response_401.py
deep_learn_ai_api_client-1.0.0.dist-info/METADATA
deep_learn_ai_api_client-1.0.0.dist-info/WHEEL
deep_learn_ai_api_client-1.0.0.dist-info/RECORD
